numberpuzzlegame/__init__.py
numberpuzzlegame/numberPuzzleGame.py
numberpuzzlegame-0.0.0.dist-info/METADATA
numberpuzzlegame-0.0.0.dist-info/WHEEL
numberpuzzlegame-0.0.0.dist-info/top_level.txt
numberpuzzlegame-0.0.0.dist-info/RECORD
