Metadata-Version: 2.1
Name: numberpuzzlegame
Version: 0.0.0
Summary: 'sliding' number puzzle game
Home-page: UNKNOWN
Author: Akhil Avvari
Author-email: <yellowloafofbread@gmail.com>
License: UNKNOWN
Keywords: python
Platform: UNKNOWN
Classifier: Development Status :: 1 - Planning
Classifier: Intended Audience :: Developers
Classifier: Programming Language :: Python :: 3
Classifier: Operating System :: Unix
Classifier: Operating System :: MacOS :: MacOS X
Classifier: Operating System :: Microsoft :: Windows
Requires-Dist: pygame
